Metadata-Version: 1.1
Name: slxvfs
Version: 0.0.1
Summary: SLX - 
Home-page: http://packages.python.org/slxvfs
Author: Sx
Author-email: orencape@gmail.com
License: UNKNOWN
Keywords: slx,slm,slf,generator,giftcard generator
Platform: UNKNOWN
Classifier: Programming Language :: Python :: 3
Classifier: Operating System :: OS Independent
